{
    "一": {
        "kana": "いち",
        "meaning": "one"
    },
    "二": {
        "kana": "に",
        "meaning": "two"
    },
    "三": {
        "kana": "さん",
        "meaning": "three"
    },
    "四": {
        "kana": "し",
        "meaning": "four"
    },
    "五": {
        "kana": "ご",
        "meaning": "five"
    },
    "六": {
        "kana": "ろく",
        "meaning": "six"
    },
    "七": {
        "kana": "しち",
        "meaning": "seven"
    },
    "八": {
        "kana": "はち",
        "meaning": "eight"
    },
    "九": {
        "kana": "きゅう",
        "meaning": "nine"
    },
    "十": {
        "kana": "じゅう",
        "meaning": "ten"
    },
    "口": {
        "kana": "くち",
        "meaning": "mouth"
    },
    "日": {
        "kana": "ひ",
        "meaning": "day"
    },
    "白": {
        "kana": "しろ",
        "meaning": "white"
    },
    "百": {
        "kana": "ひゃく",
        "meaning": "hundred"
    },
    "千": {
        "kana": "せん",
        "meaning": "thousand"
    },
    "万": {
        "kana": "まん",
        "meaning": "ten thousand"
    },
    "人": {
        "kana": "ひと",
        "meaning": "person"
    },
    "分": {
        "kana": "ふん",
        "meaning": "minute"
    },
    "土": {
        "kana": "つち",
        "meaning": "earth"
    },
    "時": {
        "kana": "とき",
        "meaning": "time"
    },
    "週": {
        "kana": "しゅう",
        "meaning": "week"
    },
    "月": {
        "kana": "つき",
        "meaning": "moon"
    },
    "午": {
        "kana": "ご",
        "meaning": "noon"
    },
    "年": {
        "kana": "とし",
        "meaning": "year"
    },
    "今": {
        "kana": "いま",
        "meaning": "now"
    },
    "木": {
        "kana": "き",
        "meaning": "tree"
    },
    "田": {
        "kana": "た",
        "meaning": "rice field"
    },
    "力": {
        "kana": "ちから",
        "meaning": "strength, power"
    },
    "前": {
        "kana": "まえ",
        "meaning": "in front of, before"
    },
    "後": {
        "kana": "あと",
        "meaning": "after, behind"
    },
    "先": {
        "kana": "さき",
        "meaning": "preceding, former"
    },
    "来": {
        "kana": "く",
        "verb": "くる",
        "meaning": "to come"
    },
    "男": {
        "kana": "おとこ",
        "meaning": "man, male"
    },
    "女": {
        "kana": "おんな",
        "meaning": "woman, female"
    },
    "子": {
        "kana": "こ",
        "meaning": "child"
    },
    "父": {
        "kana": "ちち",
        "meaning": "father"
    },
    "火": {
        "kana": "ひ",
        "meaning": "fire"
    }
}